odoo8_addon_website_sale_product_category_seo-8.0.1.0.0-py2.7-nspkg.pth
odoo8_addon_website_sale_product_category_seo-8.0.1.0.0.dist-info/top_level.txt
odoo8_addon_website_sale_product_category_seo-8.0.1.0.0.dist-info/WHEEL
odoo8_addon_website_sale_product_category_seo-8.0.1.0.0.dist-info/RECORD
odoo8_addon_website_sale_product_category_seo-8.0.1.0.0.dist-info/metadata.json
odoo8_addon_website_sale_product_category_seo-8.0.1.0.0.dist-info/DESCRIPTION.rst
odoo8_addon_website_sale_product_category_seo-8.0.1.0.0.dist-info/METADATA
odoo8_addon_website_sale_product_category_seo-8.0.1.0.0.dist-info/namespace_packages.txt
odoo_addons/website_sale_product_category_seo/__openerp__.py
odoo_addons/website_sale_product_category_seo/__init__.py
odoo_addons/website_sale_product_category_seo/README.rst
odoo_addons/website_sale_product_category_seo/models/product_public_category.py
odoo_addons/website_sale_product_category_seo/models/__init__.py
odoo_addons/website_sale_product_category_seo/i18n/it.po
odoo_addons/website_sale_product_category_seo/i18n/sl.po
odoo_addons/website_sale_product_category_seo/views/templates.xml
